pollstwo/__init__.py
pollstwo/admin.py
pollstwo/apps.py
pollstwo/models.py
pollstwo/tests.py
pollstwo/urls.py
pollstwo/views.py
pollstwo/migrations/0001_initial.py
pollstwo/migrations/__init__.py
example_pkg_django_pollstwo_1-0.0.1.dist-info/LICENSE
example_pkg_django_pollstwo_1-0.0.1.dist-info/METADATA
example_pkg_django_pollstwo_1-0.0.1.dist-info/WHEEL
example_pkg_django_pollstwo_1-0.0.1.dist-info/top_level.txt
example_pkg_django_pollstwo_1-0.0.1.dist-info/RECORD
