Metadata-Version: 2.1
Name: example-pkg-django-pollstwo-1
Version: 0.0.1
Summary: A Django app to conduct Web-based polls.
Home-page: https://github.com/bbsddn2020/django-pollstwo
Author: Lin Hai
Author-email: 177060606@qq.com
License: UNKNOWN
Platform: UNKNOWN
Classifier: Programming Language :: Python :: 3
Classifier: License :: OSI Approved :: MIT License
Classifier: Operating System :: OS Independent
Requires-Python: >=3.6
